LICENSE
MANIFEST.in
README.rst
setup.py
aino_jstools.egg-info/PKG-INFO
aino_jstools.egg-info/SOURCES.txt
aino_jstools.egg-info/dependency_links.txt
aino_jstools.egg-info/not-zip-safe
aino_jstools.egg-info/top_level.txt
jstools/__init__.py
jstools/helpers.py
jstools/importlib.py
jstools/urls.py
jstools/views.py
jstools/compiler/COPYING
jstools/compiler/README
jstools/compiler/compiler.jar
jstools/conf/__init__.py
jstools/conf/defaults.py
jstools/management/__init__.py
jstools/management/commands/__init__.py
jstools/management/commands/buildjs.py
jstools/templates/jstools/jshelper.js
jstools/templatetags/__init__.py
jstools/templatetags/jstools.py