Metadata-Version: 1.0
Name: aino-jstools
Version: 0.1.0.5
Summary: JavaScript tools for Django
Home-page: https://github.com/aino/aino-jstools
Author: Mikko Hellsing
Author-email: mikko@aino.se
License: BSD
Platform: any
Classifier: Development Status :: 3 - Alpha
Classifier: Environment :: Web Environment
Classifier: Intended Audience :: Developers
Classifier: License :: OSI Approved :: BSD License
Classifier: Operating System :: OS Independent
Classifier: Programming Language :: Python
Classifier: Programming Language :: JavaScript
Classifier: Framework :: Django
